{"name":"C01-F01-S002-01 Connect Oracle database with default settings","testSteps":[{"number":1,"description":"Given a Oracle Server","duration":3,"startTime":1509333647065,"result":"SUCCESS"},{"number":2,"description":"When I connect database with default settings","duration":1221,"startTime":1509333647068,"result":"SUCCESS"},{"number":3,"description":"Then test connection should return {successfully}","duration":2,"startTime":1509333648289,"result":"SUCCESS"}],"userStory":{"id":"c01_f01_s002_test_connection_db","storyName":"C01 f01 s002 test connection db","path":"stories/c01_configapp/c01_f01_test_connection/c01_f01_s002_test_connection_db.story","narrative":"As a user\nI want to perform an action\nSo that I can achieve a business goal","type":"story"},"title":"C01-F01-S002-01 Connect Oracle database with default settings","coreIssues":["C01-F01-S002-01"],"tags":[{"name":"2017-04","type":"relase"},{"name":"C01 configapp","type":"capability"},{"name":"ConfigAPP-API","type":"Test Type"},{"name":"C01 f01 test connection/C01 f01 s002 test connection db","type":"story"},{"name":"C01 configapp/C01 f01 test connection","type":"feature"}],"startTime":1509333647065,"duration":1227,"manual":false,"result":"SUCCESS","issues":["C01-F01-S002-01"]}